[
    {"data":{"company":{"name":"JD Inc.","contactperson":{"name":"John Doe","email":"john.doe@jdmail.com"}},"price":"1050.00","dateoforder":"12/07/2024"}},
    {"data":{"company":{"name":"Smith Enterprises","contactperson":{"name":"Jane Smith","email":"jane.smith@semail.com"}},"price":"1200.00","dateoforder":"15/07/2024"}},
    {"data":{"company":{"name":"Tech Solutions","contactperson":{"name":"Mark Brown","email":"mark.brown@tsmail.com"}},"price":"980.00","dateoforder":"18/07/2024"}},
    {"data":{"company":{"name":"Innovate LLC","contactperson":{"name":"Lucy Green","email":"lucy.green@illcmail.com"}},"price":"1150.00","dateoforder":"20/07/2024"}},
    {"data":{"company":{"name":"Global Corp","contactperson":{"name":"Michael White","email":"michael.white@gcmail.com"}},"price":"1300.00","dateoforder":"22/07/2024"}},
    {"data":{"company":{"name":"Future Tech","contactperson":{"name":"Laura Blue","email":"laura.blue@ftmail.com"}},"price":"1075.00","dateoforder":"25/07/2024"}},
    {"data":{"company":{"name":"Bright Ideas","contactperson":{"name":"David Black","email":"david.black@bimail.com"}},"price":"1250.00","dateoforder":"28/07/2024"}},
    {"data":{"company":{"name":"NextGen Inc.","contactperson":{"name":"Olivia Gray","email":"olivia.gray@ngmail.com"}},"price":"1100.00","dateoforder":"30/07/2024"}},
    {"data":{"company":{"name":"Prime Solutions","contactperson":{"name":"Paul Brown","email":"paul.brown@psmail.com"}},"price":"995.00","dateoforder":"02/08/2024"}},
    {"data":{"company":{"name":"Smart Innovations","contactperson":{"name":"Emily White","email":"emily.white@simail.com"}},"price":"1400.00","dateoforder":"05/08/2024"}},
    {"data":{"company":{"name":"Elite Enterprises","contactperson":{"name":"James Black","email":"james.black@eemail.com"}},"price":"1180.00","dateoforder":"08/08/2024"}}
]
